{
  "python": [
    "python full course",
    "python for beginners",
    "python funk",
    "python got7",
    "python course",
    "python tutorial",
    "python project"
  ],
  "saas": [
    "saas bahu ki kahani",
    "saas bahu aur flamingo",
    "saas bhi kabhi bahu thi",
    "saas marketing",
    "saas ai",
    "saas startup",
    "saas bahu",
    "saas ko'sah shrine",
    "sanson ki mala"
  ],
  "music": [
    "music for studying",
    "music for sleep",
    "music video",
    "musicfeelings",
    "music 2025",
    "musica",
    "music sounds better with you",
    "music song",
    "music relaxante"
  ],
  "trading": [
    "trading course",
    "trading for beginners",
    "tradingview",
    "trading live",
    "trading strategy",
    "trading psychology",
    "trading debutant",
    "trading 212",
    "trading app"
  ],
  "rap" :[
    "rap song",
    "raptor",
    "rap god",
    "raphael quenard",
    "rap chinois",
    "rap français 2025",
    "rap beat",
    "rap contenders"
  ],

}